demisto_client/__init__.py
demisto_client/demisto_api/README.md
demisto_client/demisto_api/__init__.py
demisto_client/demisto_api/api/__init__.py
demisto_client/demisto_api/api/default_api.py
demisto_client/demisto_api/api_client.py
demisto_client/demisto_api/configuration.py
demisto_client/demisto_api/models/__init__.py
demisto_client/demisto_api/models/advance_arg.py
demisto_client/demisto_api/models/arg_atomic_filter.py
demisto_client/demisto_api/models/arg_filter.py
demisto_client/demisto_api/models/arg_transformer.py
demisto_client/demisto_api/models/argument.py
demisto_client/demisto_api/models/array_positions.py
demisto_client/demisto_api/models/attachment.py
demisto_client/demisto_api/models/audit.py
demisto_client/demisto_api/models/audit_result.py
demisto_client/demisto_api/models/automation_script.py
demisto_client/demisto_api/models/automation_script_api.py
demisto_client/demisto_api/models/automation_script_filter.py
demisto_client/demisto_api/models/automation_script_filter_wrapper.py
demisto_client/demisto_api/models/automation_script_result.py
demisto_client/demisto_api/models/command.py
demisto_client/demisto_api/models/common_fields.py
demisto_client/demisto_api/models/complex_arg.py
demisto_client/demisto_api/models/config_data_type.py
demisto_client/demisto_api/models/config_field.py
demisto_client/demisto_api/models/create_incident_request.py
demisto_client/demisto_api/models/custom_fields.py
demisto_client/demisto_api/models/d_bot_score.py
demisto_client/demisto_api/models/dashboard.py
demisto_client/demisto_api/models/data_collection_form.py
demisto_client/demisto_api/models/date_range.py
demisto_client/demisto_api/models/date_range_filter.py
demisto_client/demisto_api/models/delete_evidence.py
demisto_client/demisto_api/models/docker_image.py
demisto_client/demisto_api/models/docker_images_result.py
demisto_client/demisto_api/models/download_entry.py
demisto_client/demisto_api/models/duration.py
demisto_py-3.3.0.dist-info/LICENSE
demisto_py-3.3.0.dist-info/METADATA
demisto_py-3.3.0.dist-info/WHEEL
demisto_py-3.3.0.dist-info/RECORD
