Metadata-Version: 2.1
Name: demisto-py
Version: 3.3.0
Summary: "A Python library for the Demisto SDK"
Home-page: https://github.com/demisto/demisto-py
License: Apache Software License
Keywords: Swagger,Demisto API
Author: Demisto
Requires-Python: >=3.8.1
Classifier: Intended Audience :: Developers
Classifier: License :: OSI Approved :: Apache Software License
Classifier: License :: Other/Proprietary License
Classifier: Natural Language :: English
Classifier: Programming Language :: Python
Classifier: Programming Language :: Python :: 3
Classifier: Programming Language :: Python :: 3.9
Classifier: Programming Language :: Python :: 3.10
Classifier: Programming Language :: Python :: 3.11
Classifier: Programming Language :: Python :: 3.8
Classifier: Programming Language :: Python :: Implementation :: CPython
Requires-Dist: certifi (>=2017.4.17)
Requires-Dist: python-dateutil (>=2.5.3)
Requires-Dist: setuptools (>=21.0.0)
Requires-Dist: six (>=1.10)
Requires-Dist: tzlocal (>=4.0.0,<5.0.0)
Requires-Dist: urllib3 (>=1.26.7)
